dexparser/__init__.py
dexparser/main.py
dexparser/helper/__init__py
dexparser/helper/logging.py
dexparser/parser/class_data_item.py
dexparser/parser/class_def_item.py
dexparser/parser/code_item.py
dexparser/parser/constants.py
dexparser/parser/encoded_catch_handler.py
dexparser/parser/encoded_field.py
dexparser/parser/encoded_method.py
dexparser/parser/encoded_type_addr_pair.py
dexparser/parser/field_id_item.py
dexparser/parser/header.py
dexparser/parser/map_item.py
dexparser/parser/map_list.py
dexparser/parser/method_id_item.py
dexparser/parser/proto_id_item.py
dexparser/parser/string_data_item.py
dexparser/parser/string_id_item.py
dexparser/parser/try_item.py
dexparser/parser/type_id_item.py
dexparser/parser/utils.py
dexparser_ag-0.0.1.dist-info/licenses/LICENSE
dexparser_ag-0.0.1.dist-info/METADATA
dexparser_ag-0.0.1.dist-info/WHEEL
dexparser_ag-0.0.1.dist-info/entry_points.txt
dexparser_ag-0.0.1.dist-info/top_level.txt
dexparser_ag-0.0.1.dist-info/RECORD
