Metadata-Version: 2.4
Name: dexparser-ag
Version: 0.0.1
Summary: DEX Parser
Author-email: anthony <ping@42.bzh>
License:                                  Apache License
Keywords: Android, Androguard, Security
Classifier: Development Status :: 4 - Beta
Classifier: License :: OSI Approved :: Apache Software License
Classifier: Programming Language :: Python
Classifier: Programming Language :: Python :: 3
Classifier: Programming Language :: Python :: 3 :: Only
Classifier: Programming Language :: Python :: 3.9
Classifier: Programming Language :: Python :: 3.10
Classifier: Programming Language :: Python :: 3.11
Classifier: Programming Language :: Python :: 3.12
Classifier: Programming Language :: Python :: 3.13
Classifier: Topic :: Security
Classifier: Topic :: Software Development
Classifier: Topic :: Utilities
Requires-Python: >=3.10
License-File: LICENSE
Requires-Dist: rich~=14.0.0
Requires-Dist: hachoir>=3.3.0
Dynamic: license-file
